reddit_mcp/__init__.py
reddit_mcp/server.py
reddit_mcp/tools/__init__.py
reddit_mcp/tools/get_comments.py
reddit_mcp/tools/get_submission.py
reddit_mcp/tools/get_subreddit.py
reddit_mcp/tools/search_posts.py
reddit_mcp/tools/search_subreddits.py
reddit_mcp/util/__init__.py
reddit_mcp/util/date_utils.py
reddit_mcp/util/reddit_client.py
reddit_mcp-0.1.2.dist-info/licenses/LICENSE
scripts/dump_schemas.py
reddit_mcp-0.1.2.dist-info/METADATA
reddit_mcp-0.1.2.dist-info/WHEEL
reddit_mcp-0.1.2.dist-info/entry_points.txt
reddit_mcp-0.1.2.dist-info/top_level.txt
reddit_mcp-0.1.2.dist-info/RECORD
