Metadata-Version: 2.4
Name: reddit-mcp
Version: 0.1.2
Summary: Reddit API tools and examples
Requires-Python: >=3.12
License-File: LICENSE
Requires-Dist: certifi>=2025.1.31
Requires-Dist: charset-normalizer>=3.4.1
Requires-Dist: idna>=3.10
Requires-Dist: praw>=7.8.1
Requires-Dist: prawcore>=2.4.0
Requires-Dist: python-dotenv>=1.0.1
Requires-Dist: requests>=2.32.3
Requires-Dist: update-checker>=0.18.0
Requires-Dist: urllib3>=2.3.0
Requires-Dist: websocket-client>=1.8.0
Requires-Dist: pydantic>=2.10.0
Requires-Dist: mcp[cli]>=1.4.1
Dynamic: license-file
